{
  "name":"1",
  "boys": [
    {
      "name":"Tom",
      "scoreReports": [
        {
          "average": 55,
          "subject": "math",
          "score": 60
        },
        {
          "average": 80,
          "subject": "English",
          "score": 91
        },
        {
          "average": 78,
          "subject": "Gym",
          "score": 40
        }
      ]

    },
    {
      "name":"Creasy",
      "scoreReports": [
        {
          "average": 55,
          "subject": "math",
          "score": 61
        },
        {
          "average": 80,
          "subject": "English",
          "score": 100
        },
        {
          "average": 78,
          "subject": "Gym",
          "score": 90
        }
      ]

    }
  ],
  "f": {
    "boys": [
      {
        "ID": "001x",
        "name": "",
        "age": 1
      },
      {
        "ID": "002x",
        "name": "boy2",
        "age": 2
      }
    ]
  },
  "产权": {
    "boys": [
      {
        "ID": "001x",
        "name": "",
        "age": 1
      },
      {
        "ID": "002x",
        "name": "boy2",
        "age": 2
      }
    ]
  },
  "bigObjKeys":{
    "boys.scoreReports": [
      "subject","average","score"
    ]
  },
  "objKeys":[
     "name",
     "age"
  ]
}